torchdescribe/__init__.py
torchdescribe/torchdescribe.py
torchdescribe-0.0.1.dist-info/LICENSE
torchdescribe-0.0.1.dist-info/METADATA
torchdescribe-0.0.1.dist-info/WHEEL
torchdescribe-0.0.1.dist-info/top_level.txt
torchdescribe-0.0.1.dist-info/RECORD
