Metadata-Version: 2.1
Name: torchdescribe
Version: 0.0.1
Summary: Describe PyTorch model in PyTorch way
Home-page: https://github.com/vidit1999/pytorch-describe
Author: Vidit Sarkar
License: MIT
Platform: UNKNOWN
Requires-Python: >=3.6
Requires-Dist: torch
